fairlib/__init__.py
fairlib/__main__.py
fairlib/dataframe/__init__.py
fairlib/dataframe/extensions.py
fairlib/inprocessing/__init__.py
fairlib/inprocessing/_torch_metrics.py
fairlib/inprocessing/adversarial_debiasing.py
fairlib/inprocessing/fauci.py
fairlib/inprocessing/in_processing.py
fairlib/inprocessing/prejudice_remover.py
fairlib/logging.py
fairlib/metrics/__init__.py
fairlib/metrics/_utils.py
fairlib/preprocessing/__init__.py
fairlib/preprocessing/disparate_impact_remover.py
fairlib/preprocessing/lfr.py
fairlib/preprocessing/pre_processing.py
fairlib/preprocessing/reweighing.py
fairlib/preprocessing/utils.py
fairlib/utils.py
aequitas_fairlib-2.8.2.dist-info/LICENSE
aequitas_fairlib-2.8.2.dist-info/METADATA
aequitas_fairlib-2.8.2.dist-info/WHEEL
aequitas_fairlib-2.8.2.dist-info/entry_points.txt
aequitas_fairlib-2.8.2.dist-info/RECORD
