Metadata-Version: 2.3
Name: aequitas-fairlib
Version: 2.8.2
Summary: A library for detecting and mitigating bias in machine learning models, with a focus on interoperability with scikit-learn, Pandas, and PyTorch.
License: Apache 2.0
Author: Valerio Di Zio
Author-email: valerio.dizio@studio.unibo.it
Requires-Python: >=3.10.0,<4.0.0
Classifier: License :: Other/Proprietary License
Classifier: Programming Language :: Python :: 3
Classifier: Programming Language :: Python :: 3.10
Classifier: Programming Language :: Python :: 3.11
Classifier: Programming Language :: Python :: 3.12
Classifier: Programming Language :: Python :: 3.13
Provides-Extra: torch
Requires-Dist: nbformat (>=5.10.4,<6.0.0)
Requires-Dist: numpy (>=2.1.3,<3.0.0)
Requires-Dist: pandas (>=2.2.2,<3.0.0)
Requires-Dist: pytest-cov (>=6.0.0,<7.0.0)
Requires-Dist: scikit-learn (>=1.5.0,<2.0.0)
Requires-Dist: scipy (>=1.15,<2.0)
Requires-Dist: torch (>=2.4.1,<3.0.0) ; extra == "torch"
